<?xml version="1.0" encoding="utf-8"?>
<poi id="chiesa_san_ciro">
    <name>Chiesa di S. Ciro</name>
    <name_long>Basilica di Santa Maria della Natività e San Ciro</name_long>
    <description>Chiesa di stile barocco siutuata in Piazza S. Ciro</description>
    <suitable_for>Tutti</suitable_for>
    <coord>40.81439, 14.33895</coord>
    <address>Piazza S. Ciro, 12</address>
    <relevance>3</relevance>
    <category id="monument" />
    <path id="itinerario_b" />
    <path id="itinerario_c" />
    <extra>
        <description_long>Distrutta la primigenia parrocchia dalla terribile eruzione del 16/17 dicembre del 1631, l'Università di Portici decise di erigerne una nuova impiantandola su un suolo già in suo possesso denominato lo Petruso. La nuova chiesa viene dunque inaugurata il 9 maggio 1642, dopo ben 10 anni d lavori. Essa è stata protagonista di numerosi restauri con conseguenti trasformazioni di cui l'ultimo effetuato nel 2012. L'odierna Chiesa di San Ciro, così chiamata in onore del Santo Patrono della citta, presenta una facciata in stile bizantino affiancata da due torri campanarie entrambe dotate di orologio. L'interno è diviso in tre navate che conducono all'altare maggiore sul quale spicca la Natività di Maria di Luca Giordano; nell'altare secondario, situato sulla destra, si trova la Concezione di Giuseppe Bonito e nella cappella a sinistra dell'altare maggiore troviamo la statua di San Ciro di Ferdinando Sperandeo. Altri lavori di Giordano e Bonito sono esposti nella sagrestia.</description_long>
        <opening_times>Lunedi-Sabato 09:45-12:00/17:00-19:00; Domenica 09:15-12:00</opening_times>
        <website>http://www.santuariosanciro.it</website>
        <image>img/chiesa_sanciro.jpg</image>
        <image>img/chiesa_sanciro2.jpg</image>
        <image>img/chiesa_sanciro3.jpg</image>
    </extra>
</poi>